INSTALL.rst
LICENSE
MANIFEST.in
README.rst
VERSION
requirements.txt
setup.py
tasks.py
src/flyer/MenuPrincipal.py
src/flyer/__init__.py
src/flyer/__main__.py
src/flyer/__meta__.py
src/flyer.egg-info/PKG-INFO
src/flyer.egg-info/SOURCES.txt
src/flyer.egg-info/dependency_links.txt
src/flyer.egg-info/not-zip-safe
src/flyer.egg-info/requires.txt
src/flyer.egg-info/top_level.txt
src/flyer/tests/__init__.py
src/flyer/tests/__main__.py
src/flyer/tests/test_documentation.py
src/flyer/tests/test_flyer.py