Metadata-Version: 1.1
Name: flyer
Version: 0.1.1
Summary: A game to beat your points
Home-page: https://github.com/LeonardoRk/Flyer.git
Author: Leonardo Arthur and Victor Hugo
Author-email: leodegolim@yahoo.com.br
License: UNKNOWN
Platform: linux
Classifier: Development Status :: 3 - Alpha
Classifier: Intended Audience :: Developers
Classifier: License :: OSI Approved :: GNU General Public License (GPL)
Classifier: Operating System :: OS Independent
Classifier: Programming Language :: Python
Classifier: Programming Language :: Python :: 3
Classifier: Programming Language :: Python :: 3.3
Classifier: Programming Language :: Python :: 3.4
Classifier: Programming Language :: Python :: 3.5
Classifier: Topic :: Software Development :: Libraries
